{
  "schedules": [
    {
      "name": "Nonres_Cool_Sch",
      "template": "179d-90.1-2007",
      "category": "Cooling",
      "units": "C",
      "day_types": "Default|SmrDsn|WntrDsn|Hol",
      "start_date": "2014-01-01T00:00:00+00:00",
      "end_date": "2014-12-31T00:00:00+00:00",
      "type": "Hourly",
      "notes": "ACM 2005 Table 2-5 Nonresidential",
      "values": [
        25,
        25,
        25,
        25,
        25,
        22.8,
        22.8,
        22.8,
        22.8,
        22.8,
        22.8,
        22.8,
        22.8,
        22.8,
        22.8,
        22.8,
        22.8,
        22.8,
        25,
        25,
        25,
        25,
        25,
        25
      ]
    },
    {
      "name": "Nonres_Equip_Sch",
      "template": "179d-90.1-2007",
      "category": "Equipment",
      "units": null,
      "day_types": "Sat",
      "start_date": "2014-01-01T00:00:00+00:00",
      "end_date": "2014-12-31T00:00:00+00:00",
      "type": "Hourly",
      "notes": "ACM 2005 Table 2-5 Nonresidential",
      "values": [
        0.15,
        0.15,
        0.15,
        0.15,
        0.15,
        0.15,
        0.15,
        0.2,
        0.25,
        0.25,
        0.25,
        0.25,
        0.25,
        0.25,
        0.2,
        0.2,
        0.2,
        0.15,
        0.15,
        0.15,
        0.15,
        0.15,
        0.15,
        0.15
      ]
    },
    {
      "name": "Nonres_Equip_Sch",
      "template": "179d-90.1-2007",
      "category": "Equipment",
      "units": null,
      "day_types": "SmrDsn|Hol",
      "start_date": "2014-01-01T00:00:00+00:00",
      "end_date": "2014-12-31T00:00:00+00:00",
      "type": "Constant",
      "notes": "ACM 2005 Table 2-5 Nonresidential",
      "values": [
        1
      ]
    },
    {
      "name": "Nonres_Equip_Sch",
      "template": "179d-90.1-2007",
      "category": "Equipment",
      "units": null,
      "day_types": "Sun",
      "start_date": "2014-01-01T00:00:00+00:00",
      "end_date": "2014-12-31T00:00:00+00:00",
      "type": "Hourly",
      "notes": "ACM 2005 Table 2-5 Nonresidential",
      "values": [
        0.15,
        0.15,
        0.15,
        0.15,
        0.15,
        0.15,
        0.15,
        0.2,
        0.2,
        0.2,
        0.2,
        0.2,
        0.2,
        0.2,
        0.2,
        0.2,
        0.2,
        0.15,
        0.15,
        0.15,
        0.15,
        0.15,
        0.15,
        0.15
      ]
    },
    {
      "name": "Nonres_Equip_Sch",
      "template": "179d-90.1-2007",
      "category": "Equipment",
      "units": null,
      "day_types": "Wkdy",
      "start_date": "2014-01-01T00:00:00+00:00",
      "end_date": "2014-12-31T00:00:00+00:00",
      "type": "Hourly",
      "notes": "ACM 2005 Table 2-5 Nonresidential",
      "values": [
        0.15,
        0.15,
        0.15,
        0.15,
        0.15,
        0.2,
        0.35,
        0.6,
        0.7,
        0.7,
        0.7,
        0.7,
        0.7,
        0.7,
        0.7,
        0.7,
        0.65,
        0.45,
        0.3,
        0.2,
        0.2,
        0.15,
        0.15,
        0.15
      ]
    },
    {
      "name": "Nonres_Equip_Sch",
      "template": "179d-90.1-2007",
      "category": "Equipment",
      "units": null,
      "day_types": "WntrDsn",
      "start_date": "2014-01-01T00:00:00+00:00",
      "end_date": "2014-12-31T00:00:00+00:00",
      "type": "Constant",
      "notes": "ACM 2005 Table 2-5 Nonresidential",
      "values": [
        0
      ]
    },
    {
      "name": "Nonres_HVAC_Sch",
      "template": "179d-90.1-2007",
      "category": "Operation",
      "units": null,
      "day_types": "Sat",
      "start_date": "2014-01-01T00:00:00+00:00",
      "end_date": "2014-12-31T00:00:00+00:00",
      "type": "Hourly",
      "notes": "ACM 2005 Table 2-5 Nonresidential",
      "values": [
        0,
        0,
        0,
        0,
        1,
        1,
        1,
        1,
        1,
        1,
        1,
        1,
        1,
        1,
        1,
        0,
        0,
        0,
        0,
        0,
        0,
        0,
        0,
        0
      ]
    },
    {
      "name": "Nonres_HVAC_Sch",
      "template": "179d-90.1-2007",
      "category": "Operation",
      "units": null,
      "day_types": "Sun",
      "start_date": "2014-01-01T00:00:00+00:00",
      "end_date": "2014-12-31T00:00:00+00:00",
      "type": "Constant",
      "notes": "ACM 2005 Table 2-5 Nonresidential",
      "values": [
        0
      ]
    },
    {
      "name": "Nonres_HVAC_Sch",
      "template": "179d-90.1-2007",
      "category": "Operation",
      "units": null,
      "day_types": "Wkdy|SmrDsn|WntrDsn|Hol",
      "start_date": "2014-01-01T00:00:00+00:00",
      "end_date": "2014-12-31T00:00:00+00:00",
      "type": "Hourly",
      "notes": "ACM 2005 Table 2-5 Nonresidential",
      "values": [
        0,
        0,
        0,
        0,
        0,
        1,
        1,
        1,
        1,
        1,
        1,
        1,
        1,
        1,
        1,
        1,
        1,
        1,
        1,
        1,
        0,
        0,
        0,
        0
      ]
    },
    {
      "name": "Nonres_Heat_Sch",
      "template": "179d-90.1-2007",
      "category": "Heating",
      "units": "C",
      "day_types": "Wkdy|SmrDsn|WntrDsn|Hol",
      "start_date": "2014-01-01T00:00:00+00:00",
      "end_date": "2014-12-31T00:00:00+00:00",
      "type": "Hourly",
      "notes": "ACM 2005 Table 2-5 Nonresidential",
      "values": [
        15.6,
        15.6,
        15.6,
        15.6,
        15.6,
        18.3,
        18.3,
        21.1,
        21.1,
        21.1,
        21.1,
        21.1,
        21.1,
        21.1,
        21.1,
        21.1,
        21.1,
        21.1,
        18.3,
        15.6,
        15.6,
        15.6,
        15.6,
        15.6
      ]
    },
    {
      "name": "Nonres_Heat_Sch",
      "template": "179d-90.1-2007",
      "category": "Heating",
      "units": "C",
      "day_types": "Wknd",
      "start_date": "2014-01-01T00:00:00+00:00",
      "end_date": "2014-12-31T00:00:00+00:00",
      "type": "Hourly",
      "notes": "ACM 2005 Table 2-5 Nonresidential",
      "values": [
        15.6,
        15.6,
        15.6,
        15.6,
        15.6,
        18.3,
        18.3,
        18.3,
        18.3,
        18.3,
        18.3,
        18.3,
        18.3,
        18.3,
        18.3,
        18.3,
        15.6,
        15.6,
        15.6,
        15.6,
        15.6,
        15.6,
        15.6,
        15.6
      ]
    },
    {
      "name": "Nonres_Infil_Sch",
      "template": "179d-90.1-2007",
      "category": "Infiltration",
      "units": null,
      "day_types": "Sat|WntDsn",
      "start_date": "2014-01-01T00:00:00+00:00",
      "end_date": "2014-12-31T00:00:00+00:00",
      "type": "Hourly",
      "notes": "ACM 2005 Table 2-5 Nonresidential",
      "values": [
        1,
        1,
        1,
        1,
        1,
        0,
        0,
        0,
        0,
        0,
        0,
        0,
        0,
        0,
        0,
        1,
        1,
        1,
        1,
        1,
        1,
        1,
        1,
        1
      ]
    },
    {
      "name": "Nonres_Infil_Sch",
      "template": "179d-90.1-2007",
      "category": "Infiltration",
      "units": null,
      "day_types": "Sun|Hol",
      "start_date": "2014-01-01T00:00:00+00:00",
      "end_date": "2014-12-31T00:00:00+00:00",
      "type": "Constant",
      "notes": "ACM 2005 Table 2-5 Nonresidential",
      "values": [
        1
      ]
    },
    {
      "name": "Nonres_Infil_Sch",
      "template": "179d-90.1-2007",
      "category": "Infiltration",
      "units": null,
      "day_types": "Wkdy|SmrDsn",
      "start_date": "2014-01-01T00:00:00+00:00",
      "end_date": "2014-12-31T00:00:00+00:00",
      "type": "Hourly",
      "notes": "ACM 2005 Table 2-5 Nonresidential",
      "values": [
        1,
        1,
        1,
        1,
        1,
        0,
        0,
        0,
        0,
        0,
        0,
        0,
        0,
        0,
        0,
        0,
        0,
        0,
        0,
        0,
        1,
        1,
        1,
        1
      ]
    },
    {
      "name": "Nonres_Light_Sch",
      "template": "179d-90.1-2007",
      "category": "Lighting",
      "units": null,
      "day_types": "Sat",
      "start_date": "2014-01-01T00:00:00+00:00",
      "end_date": "2014-12-31T00:00:00+00:00",
      "type": "Hourly",
      "notes": "ACM 2005 Table 2-5 Nonresidential",
      "values": [
        0.05,
        0.05,
        0.05,
        0.05,
        0.05,
        0.1,
        0.15,
        0.25,
        0.25,
        0.25,
        0.25,
        0.25,
        0.25,
        0.25,
        0.2,
        0.2,
        0.2,
        0.15,
        0.1,
        0.1,
        0.1,
        0.1,
        0.1,
        0.1
      ]
    },
    {
      "name": "Nonres_Light_Sch",
      "template": "179d-90.1-2007",
      "category": "Lighting",
      "units": null,
      "day_types": "SmrDsn|Hol",
      "start_date": "2014-01-01T00:00:00+00:00",
      "end_date": "2014-12-31T00:00:00+00:00",
      "type": "Constant",
      "notes": "ACM 2005 Table 2-5 Nonresidential",
      "values": [
        1
      ]
    },
    {
      "name": "Nonres_Light_Sch",
      "template": "179d-90.1-2007",
      "category": "Lighting",
      "units": null,
      "day_types": "Sun",
      "start_date": "2014-01-01T00:00:00+00:00",
      "end_date": "2014-12-31T00:00:00+00:00",
      "type": "Hourly",
      "notes": "ACM 2005 Table 2-5 Nonresidential",
      "values": [
        0.05,
        0.05,
        0.05,
        0.05,
        0.05,
        0.1,
        0.1,
        0.15,
        0.15,
        0.15,
        0.15,
        0.15,
        0.15,
        0.15,
        0.15,
        0.15,
        0.15,
        0.1,
        0.1,
        0.1,
        0.05,
        0.05,
        0.05,
        0.05
      ]
    },
    {
      "name": "Nonres_Light_Sch",
      "template": "179d-90.1-2007",
      "category": "Lighting",
      "units": null,
      "day_types": "Wkdy",
      "start_date": "2014-01-01T00:00:00+00:00",
      "end_date": "2014-12-31T00:00:00+00:00",
      "type": "Hourly",
      "notes": "ACM 2005 Table 2-5 Nonresidential",
      "values": [
        0.05,
        0.05,
        0.05,
        0.05,
        0.1,
        0.2,
        0.4,
        0.7,
        0.8,
        0.85,
        0.85,
        0.85,
        0.85,
        0.85,
        0.85,
        0.85,
        0.85,
        0.8,
        0.35,
        0.1,
        0.1,
        0.1,
        0.1,
        0.1
      ]
    },
    {
      "name": "Nonres_Light_Sch",
      "template": "179d-90.1-2007",
      "category": "Lighting",
      "units": null,
      "day_types": "WntrDsn",
      "start_date": "2014-01-01T00:00:00+00:00",
      "end_date": "2014-12-31T00:00:00+00:00",
      "type": "Constant",
      "notes": "ACM 2005 Table 2-5 Nonresidential",
      "values": [
        0
      ]
    },
    {
      "name": "Nonres_Occ_Sch",
      "template": "179d-90.1-2007",
      "category": "Occupancy",
      "units": null,
      "day_types": "Sat",
      "start_date": "2014-01-01T00:00:00+00:00",
      "end_date": "2014-12-31T00:00:00+00:00",
      "type": "Hourly",
      "notes": "ACM 2005 Table 2-5 Nonresidential",
      "values": [
        0,
        0,
        0,
        0,
        0,
        0,
        0.05,
        0.15,
        0.15,
        0.15,
        0.15,
        0.15,
        0.15,
        0.15,
        0.15,
        0.15,
        0.15,
        0.05,
        0.05,
        0.05,
        0,
        0,
        0,
        0
      ]
    },
    {
      "name": "Nonres_Occ_Sch",
      "template": "179d-90.1-2007",
      "category": "Occupancy",
      "units": null,
      "day_types": "SmrDsn|Hol",
      "start_date": "2014-01-01T00:00:00+00:00",
      "end_date": "2014-12-31T00:00:00+00:00",
      "type": "Hourly",
      "notes": "ACM 2005 Table 2-5 Nonresidential",
      "values": [
        0,
        0,
        0,
        0,
        1,
        1,
        1,
        1,
        1,
        1,
        1,
        1,
        1,
        1,
        1,
        1,
        1,
        1,
        1,
        1,
        1,
        1,
        1,
        0
      ]
    },
    {
      "name": "Nonres_Occ_Sch",
      "template": "179d-90.1-2007",
      "category": "Occupancy",
      "units": null,
      "day_types": "Sun",
      "start_date": "2014-01-01T00:00:00+00:00",
      "end_date": "2014-12-31T00:00:00+00:00",
      "type": "Hourly",
      "notes": "ACM 2005 Table 2-5 Nonresidential",
      "values": [
        0,
        0,
        0,
        0,
        0,
        0,
        0,
        0.05,
        0.05,
        0.05,
        0.05,
        0.05,
        0.05,
        0.05,
        0.05,
        0.05,
        0.05,
        0.05,
        0.05,
        0.05,
        0,
        0,
        0,
        0
      ]
    },
    {
      "name": "Nonres_Occ_Sch",
      "template": "179d-90.1-2007",
      "category": "Occupancy",
      "units": null,
      "day_types": "Wkdy",
      "start_date": "2014-01-01T00:00:00+00:00",
      "end_date": "2014-12-31T00:00:00+00:00",
      "type": "Hourly",
      "notes": "ACM 2005 Table 2-5 Nonresidential",
      "values": [
        0,
        0,
        0,
        0,
        0.05,
        0.1,
        0.25,
        0.65,
        0.65,
        0.65,
        0.65,
        0.65,
        0.65,
        0.65,
        0.65,
        0.65,
        0.65,
        0.4,
        0.25,
        0.1,
        0.05,
        0.05,
        0.05,
        0
      ]
    },
    {
      "name": "Nonres_Occ_Sch",
      "template": "179d-90.1-2007",
      "category": "Occupancy",
      "units": null,
      "day_types": "WntrDsn",
      "start_date": "2014-01-01T00:00:00+00:00",
      "end_date": "2014-12-31T00:00:00+00:00",
      "type": "Hourly",
      "notes": "ACM 2005 Table 2-5 Nonresidential",
      "values": [
        0,
        0,
        0,
        0,
        0.05,
        0.05,
        0.05,
        0.05,
        0.05,
        0.05,
        0.05,
        0.05,
        0.05,
        0.05,
        0.05,
        0.05,
        0.05,
        0.05,
        0.05,
        0.05,
        0.05,
        0.05,
        0.05,
        0
      ]
    },
    {
      "name": "Nonres_SWH_Sch",
      "template": "179d-90.1-2007",
      "category": "Service Water Heating",
      "units": null,
      "day_types": "Wkdy|SmrDsn|WntrDsn|Hol",
      "start_date": "2014-01-01T00:00:00+00:00",
      "end_date": "2014-12-31T00:00:00+00:00",
      "type": "Hourly",
      "notes": "ACM 2005 Table 2-5 Nonresidential",
      "values": [
        0,
        0,
        0,
        0,
        0.1,
        0.1,
        0.5,
        0.5,
        0.5,
        0.5,
        0.7,
        0.9,
        0.9,
        0.5,
        0.5,
        0.7,
        0.5,
        0.5,
        0.5,
        0.1,
        0.1,
        0.1,
        0.1,
        0
      ]
    }
  ]
}