{
  "energy_recovery": [
    {
      "climate_zone": "0A",
      "under_8000_hours": true,
      "nontransient_dwelling": "Any",
      "percent_oa_0_to_10": null,
      "percent_oa_10_to_20": 26000,
      "percent_oa_20_to_30": 16000,
      "percent_oa_30_to_40": 5500,
      "percent_oa_40_to_50": 4500,
      "percent_oa_50_to_60": 3500,
      "percent_oa_60_to_70": 2000,
      "percent_oa_70_to_80": 1000,
      "percent_oa_greater_than_80": 0,
      "design_conditions": "Cooling",
      "energy_recovery_effectiveness": 0.5,
      "enthalpy_recovery_ratio": null,
      "sensible_energy_recovery_ratio": null
    },
    {
      "climate_zone": "0A",
      "under_8000_hours": false,
      "nontransient_dwelling": "Any",
      "percent_oa_0_to_10": null,
      "percent_oa_10_to_20": 2500,
      "percent_oa_20_to_30": 2000,
      "percent_oa_30_to_40": 1000,
      "percent_oa_40_to_50": 500,
      "percent_oa_50_to_60": 0,
      "percent_oa_60_to_70": 0,
      "percent_oa_70_to_80": 0,
      "percent_oa_greater_than_80": 0,
      "design_conditions": "Cooling",
      "energy_recovery_effectiveness": 0.5,
      "enthalpy_recovery_ratio": null,
      "sensible_energy_recovery_ratio": null
    },
    {
      "climate_zone": "0B",
      "under_8000_hours": true,
      "nontransient_dwelling": "Any",
      "percent_oa_0_to_10": null,
      "percent_oa_10_to_20": null,
      "percent_oa_20_to_30": null,
      "percent_oa_30_to_40": null,
      "percent_oa_40_to_50": null,
      "percent_oa_50_to_60": 26000,
      "percent_oa_60_to_70": 12000,
      "percent_oa_70_to_80": 5000,
      "percent_oa_greater_than_80": 4000,
      "design_conditions": "Cooling",
      "energy_recovery_effectiveness": 0.5,
      "enthalpy_recovery_ratio": null,
      "sensible_energy_recovery_ratio": null
    },
    {
      "climate_zone": "0B",
      "under_8000_hours": false,
      "nontransient_dwelling": "Any",
      "percent_oa_0_to_10": null,
      "percent_oa_10_to_20": null,
      "percent_oa_20_to_30": 19500,
      "percent_oa_30_to_40": 9000,
      "percent_oa_40_to_50": 5000,
      "percent_oa_50_to_60": 4000,
      "percent_oa_60_to_70": 3000,
      "percent_oa_70_to_80": 1500,
      "percent_oa_greater_than_80": 0,
      "design_conditions": "Cooling",
      "energy_recovery_effectiveness": 0.5,
      "enthalpy_recovery_ratio": null,
      "sensible_energy_recovery_ratio": null
    },
    {
      "climate_zone": "1A",
      "under_8000_hours": true,
      "nontransient_dwelling": "Any",
      "percent_oa_0_to_10": null,
      "percent_oa_10_to_20": 26000,
      "percent_oa_20_to_30": 16000,
      "percent_oa_30_to_40": 5500,
      "percent_oa_40_to_50": 4500,
      "percent_oa_50_to_60": 3500,
      "percent_oa_60_to_70": 2000,
      "percent_oa_70_to_80": 1000,
      "percent_oa_greater_than_80": 0,
      "design_conditions": "Cooling",
      "energy_recovery_effectiveness": 0.5,
      "enthalpy_recovery_ratio": null,
      "sensible_energy_recovery_ratio": null
    },
    {
      "climate_zone": "1A",
      "under_8000_hours": false,
      "nontransient_dwelling": "Any",
      "percent_oa_0_to_10": null,
      "percent_oa_10_to_20": 2500,
      "percent_oa_20_to_30": 2000,
      "percent_oa_30_to_40": 1000,
      "percent_oa_40_to_50": 500,
      "percent_oa_50_to_60": 0,
      "percent_oa_60_to_70": 0,
      "percent_oa_70_to_80": 0,
      "percent_oa_greater_than_80": 0,
      "design_conditions": "Cooling",
      "energy_recovery_effectiveness": 0.5,
      "enthalpy_recovery_ratio": null,
      "sensible_energy_recovery_ratio": null
    },
    {
      "climate_zone": "1B",
      "under_8000_hours": true,
      "nontransient_dwelling": "Any",
      "percent_oa_0_to_10": null,
      "percent_oa_10_to_20": null,
      "percent_oa_20_to_30": null,
      "percent_oa_30_to_40": null,
      "percent_oa_40_to_50": null,
      "percent_oa_50_to_60": 26000,
      "percent_oa_60_to_70": 12000,
      "percent_oa_70_to_80": 5000,
      "percent_oa_greater_than_80": 4000,
      "design_conditions": "Cooling",
      "energy_recovery_effectiveness": 0.5,
      "enthalpy_recovery_ratio": null,
      "sensible_energy_recovery_ratio": null
    },
    {
      "climate_zone": "1B",
      "under_8000_hours": false,
      "nontransient_dwelling": "Any",
      "percent_oa_0_to_10": null,
      "percent_oa_10_to_20": null,
      "percent_oa_20_to_30": 19500,
      "percent_oa_30_to_40": 9000,
      "percent_oa_40_to_50": 5000,
      "percent_oa_50_to_60": 4000,
      "percent_oa_60_to_70": 3000,
      "percent_oa_70_to_80": 1500,
      "percent_oa_greater_than_80": 0,
      "design_conditions": "Cooling",
      "energy_recovery_effectiveness": 0.5,
      "enthalpy_recovery_ratio": null,
      "sensible_energy_recovery_ratio": null
    },
    {
      "climate_zone": "2A",
      "under_8000_hours": true,
      "nontransient_dwelling": "Any",
      "percent_oa_0_to_10": null,
      "percent_oa_10_to_20": 26000,
      "percent_oa_20_to_30": 16000,
      "percent_oa_30_to_40": 5500,
      "percent_oa_40_to_50": 4500,
      "percent_oa_50_to_60": 3500,
      "percent_oa_60_to_70": 2000,
      "percent_oa_70_to_80": 1000,
      "percent_oa_greater_than_80": 0,
      "design_conditions": "Cooling",
      "energy_recovery_effectiveness": 0.5,
      "enthalpy_recovery_ratio": null,
      "sensible_energy_recovery_ratio": null
    },
    {
      "climate_zone": "2A",
      "under_8000_hours": false,
      "nontransient_dwelling": "Any",
      "percent_oa_0_to_10": null,
      "percent_oa_10_to_20": 2500,
      "percent_oa_20_to_30": 2000,
      "percent_oa_30_to_40": 1000,
      "percent_oa_40_to_50": 500,
      "percent_oa_50_to_60": 0,
      "percent_oa_60_to_70": 0,
      "percent_oa_70_to_80": 0,
      "percent_oa_greater_than_80": 0,
      "design_conditions": "Cooling",
      "energy_recovery_effectiveness": 0.5,
      "enthalpy_recovery_ratio": null,
      "sensible_energy_recovery_ratio": null
    },
    {
      "climate_zone": "2B",
      "under_8000_hours": true,
      "nontransient_dwelling": "Any",
      "percent_oa_0_to_10": null,
      "percent_oa_10_to_20": null,
      "percent_oa_20_to_30": null,
      "percent_oa_30_to_40": null,
      "percent_oa_40_to_50": null,
      "percent_oa_50_to_60": 26000,
      "percent_oa_60_to_70": 12000,
      "percent_oa_70_to_80": 5000,
      "percent_oa_greater_than_80": 4000,
      "design_conditions": "Cooling",
      "energy_recovery_effectiveness": 0.5,
      "enthalpy_recovery_ratio": null,
      "sensible_energy_recovery_ratio": null
    },
    {
      "climate_zone": "2B",
      "under_8000_hours": false,
      "nontransient_dwelling": "Any",
      "percent_oa_0_to_10": null,
      "percent_oa_10_to_20": null,
      "percent_oa_20_to_30": 19500,
      "percent_oa_30_to_40": 9000,
      "percent_oa_40_to_50": 5000,
      "percent_oa_50_to_60": 4000,
      "percent_oa_60_to_70": 3000,
      "percent_oa_70_to_80": 1500,
      "percent_oa_greater_than_80": 0,
      "design_conditions": "Cooling",
      "energy_recovery_effectiveness": 0.5,
      "enthalpy_recovery_ratio": null,
      "sensible_energy_recovery_ratio": null
    },
    {
      "climate_zone": "0A",
      "under_8000_hours": true,
      "nontransient_dwelling": "Any",
      "percent_oa_0_to_10": null,
      "percent_oa_10_to_20": null,
      "percent_oa_20_to_30": null,
      "percent_oa_30_to_40": null,
      "percent_oa_40_to_50": null,
      "percent_oa_50_to_60": null,
      "percent_oa_60_to_70": null,
      "percent_oa_70_to_80": null,
      "percent_oa_greater_than_80": null,
      "design_conditions": "Heating",
      "energy_recovery_effectiveness": null,
      "enthalpy_recovery_ratio": null,
      "sensible_energy_recovery_ratio": null
    },
    {
      "climate_zone": "0A",
      "under_8000_hours": false,
      "nontransient_dwelling": "Any",
      "percent_oa_0_to_10": null,
      "percent_oa_10_to_20": null,
      "percent_oa_20_to_30": null,
      "percent_oa_30_to_40": null,
      "percent_oa_40_to_50": null,
      "percent_oa_50_to_60": null,
      "percent_oa_60_to_70": null,
      "percent_oa_70_to_80": null,
      "percent_oa_greater_than_80": null,
      "design_conditions": "Heating",
      "energy_recovery_effectiveness": null,
      "enthalpy_recovery_ratio": null,
      "sensible_energy_recovery_ratio": null
    },
    {
      "climate_zone": "0B",
      "under_8000_hours": true,
      "nontransient_dwelling": "Any",
      "percent_oa_0_to_10": null,
      "percent_oa_10_to_20": null,
      "percent_oa_20_to_30": null,
      "percent_oa_30_to_40": null,
      "percent_oa_40_to_50": null,
      "percent_oa_50_to_60": null,
      "percent_oa_60_to_70": null,
      "percent_oa_70_to_80": null,
      "percent_oa_greater_than_80": null,
      "design_conditions": "Heating",
      "energy_recovery_effectiveness": null,
      "enthalpy_recovery_ratio": null,
      "sensible_energy_recovery_ratio": null
    },
    {
      "climate_zone": "0B",
      "under_8000_hours": false,
      "nontransient_dwelling": "Any",
      "percent_oa_0_to_10": null,
      "percent_oa_10_to_20": null,
      "percent_oa_20_to_30": null,
      "percent_oa_30_to_40": null,
      "percent_oa_40_to_50": null,
      "percent_oa_50_to_60": null,
      "percent_oa_60_to_70": null,
      "percent_oa_70_to_80": null,
      "percent_oa_greater_than_80": null,
      "design_conditions": "Heating",
      "energy_recovery_effectiveness": null,
      "enthalpy_recovery_ratio": null,
      "sensible_energy_recovery_ratio": null
    },
    {
      "climate_zone": "1A",
      "under_8000_hours": true,
      "nontransient_dwelling": "Any",
      "percent_oa_0_to_10": null,
      "percent_oa_10_to_20": null,
      "percent_oa_20_to_30": null,
      "percent_oa_30_to_40": null,
      "percent_oa_40_to_50": null,
      "percent_oa_50_to_60": null,
      "percent_oa_60_to_70": null,
      "percent_oa_70_to_80": null,
      "percent_oa_greater_than_80": null,
      "design_conditions": "Heating",
      "energy_recovery_effectiveness": null,
      "enthalpy_recovery_ratio": null,
      "sensible_energy_recovery_ratio": null
    },
    {
      "climate_zone": "1A",
      "under_8000_hours": false,
      "nontransient_dwelling": "Any",
      "percent_oa_0_to_10": null,
      "percent_oa_10_to_20": null,
      "percent_oa_20_to_30": null,
      "percent_oa_30_to_40": null,
      "percent_oa_40_to_50": null,
      "percent_oa_50_to_60": null,
      "percent_oa_60_to_70": null,
      "percent_oa_70_to_80": null,
      "percent_oa_greater_than_80": null,
      "design_conditions": "Heating",
      "energy_recovery_effectiveness": null,
      "enthalpy_recovery_ratio": null,
      "sensible_energy_recovery_ratio": null
    },
    {
      "climate_zone": "1B",
      "under_8000_hours": true,
      "nontransient_dwelling": "Any",
      "percent_oa_0_to_10": null,
      "percent_oa_10_to_20": null,
      "percent_oa_20_to_30": null,
      "percent_oa_30_to_40": null,
      "percent_oa_40_to_50": null,
      "percent_oa_50_to_60": null,
      "percent_oa_60_to_70": null,
      "percent_oa_70_to_80": null,
      "percent_oa_greater_than_80": null,
      "design_conditions": "Heating",
      "energy_recovery_effectiveness": null,
      "enthalpy_recovery_ratio": null,
      "sensible_energy_recovery_ratio": null
    },
    {
      "climate_zone": "1B",
      "under_8000_hours": false,
      "nontransient_dwelling": "Any",
      "percent_oa_0_to_10": null,
      "percent_oa_10_to_20": null,
      "percent_oa_20_to_30": null,
      "percent_oa_30_to_40": null,
      "percent_oa_40_to_50": null,
      "percent_oa_50_to_60": null,
      "percent_oa_60_to_70": null,
      "percent_oa_70_to_80": null,
      "percent_oa_greater_than_80": null,
      "design_conditions": "Heating",
      "energy_recovery_effectiveness": null,
      "enthalpy_recovery_ratio": null,
      "sensible_energy_recovery_ratio": null
    },
    {
      "climate_zone": "2A",
      "under_8000_hours": true,
      "nontransient_dwelling": "Any",
      "percent_oa_0_to_10": null,
      "percent_oa_10_to_20": null,
      "percent_oa_20_to_30": null,
      "percent_oa_30_to_40": null,
      "percent_oa_40_to_50": null,
      "percent_oa_50_to_60": null,
      "percent_oa_60_to_70": null,
      "percent_oa_70_to_80": null,
      "percent_oa_greater_than_80": null,
      "design_conditions": "Heating",
      "energy_recovery_effectiveness": null,
      "enthalpy_recovery_ratio": null,
      "sensible_energy_recovery_ratio": null
    },
    {
      "climate_zone": "2A",
      "under_8000_hours": false,
      "nontransient_dwelling": "Any",
      "percent_oa_0_to_10": null,
      "percent_oa_10_to_20": null,
      "percent_oa_20_to_30": null,
      "percent_oa_30_to_40": null,
      "percent_oa_40_to_50": null,
      "percent_oa_50_to_60": null,
      "percent_oa_60_to_70": null,
      "percent_oa_70_to_80": null,
      "percent_oa_greater_than_80": null,
      "design_conditions": "Heating",
      "energy_recovery_effectiveness": null,
      "enthalpy_recovery_ratio": null,
      "sensible_energy_recovery_ratio": null
    },
    {
      "climate_zone": "2B",
      "under_8000_hours": true,
      "nontransient_dwelling": "Any",
      "percent_oa_0_to_10": null,
      "percent_oa_10_to_20": null,
      "percent_oa_20_to_30": null,
      "percent_oa_30_to_40": null,
      "percent_oa_40_to_50": null,
      "percent_oa_50_to_60": null,
      "percent_oa_60_to_70": null,
      "percent_oa_70_to_80": null,
      "percent_oa_greater_than_80": null,
      "design_conditions": "Heating",
      "energy_recovery_effectiveness": null,
      "enthalpy_recovery_ratio": null,
      "sensible_energy_recovery_ratio": null
    },
    {
      "climate_zone": "2B",
      "under_8000_hours": false,
      "nontransient_dwelling": "Any",
      "percent_oa_0_to_10": null,
      "percent_oa_10_to_20": null,
      "percent_oa_20_to_30": null,
      "percent_oa_30_to_40": null,
      "percent_oa_40_to_50": null,
      "percent_oa_50_to_60": null,
      "percent_oa_60_to_70": null,
      "percent_oa_70_to_80": null,
      "percent_oa_greater_than_80": null,
      "design_conditions": "Heating",
      "energy_recovery_effectiveness": null,
      "enthalpy_recovery_ratio": null,
      "sensible_energy_recovery_ratio": null
    },
    {
      "climate_zone": "3A",
      "under_8000_hours": true,
      "nontransient_dwelling": "Any",
      "percent_oa_0_to_10": null,
      "percent_oa_10_to_20": 26000,
      "percent_oa_20_to_30": 16000,
      "percent_oa_30_to_40": 5500,
      "percent_oa_40_to_50": 4500,
      "percent_oa_50_to_60": 3500,
      "percent_oa_60_to_70": 2000,
      "percent_oa_70_to_80": 1000,
      "percent_oa_greater_than_80": 0,
      "design_conditions": "Heating",
      "energy_recovery_effectiveness": 0.5,
      "enthalpy_recovery_ratio": null,
      "sensible_energy_recovery_ratio": null
    },
    {
      "climate_zone": "3A",
      "under_8000_hours": false,
      "nontransient_dwelling": "Any",
      "percent_oa_0_to_10": null,
      "percent_oa_10_to_20": 2500,
      "percent_oa_20_to_30": 2000,
      "percent_oa_30_to_40": 1000,
      "percent_oa_40_to_50": 500,
      "percent_oa_50_to_60": 0,
      "percent_oa_60_to_70": 0,
      "percent_oa_70_to_80": 0,
      "percent_oa_greater_than_80": 0,
      "design_conditions": "Heating",
      "energy_recovery_effectiveness": 0.5,
      "enthalpy_recovery_ratio": null,
      "sensible_energy_recovery_ratio": null
    },
    {
      "climate_zone": "3A",
      "under_8000_hours": true,
      "nontransient_dwelling": "Any",
      "percent_oa_0_to_10": null,
      "percent_oa_10_to_20": 26000,
      "percent_oa_20_to_30": 16000,
      "percent_oa_30_to_40": 5500,
      "percent_oa_40_to_50": 4500,
      "percent_oa_50_to_60": 3500,
      "percent_oa_60_to_70": 2000,
      "percent_oa_70_to_80": 1000,
      "percent_oa_greater_than_80": 0,
      "design_conditions": "Cooling",
      "energy_recovery_effectiveness": 0.5,
      "enthalpy_recovery_ratio": null,
      "sensible_energy_recovery_ratio": null
    },
    {
      "climate_zone": "3A",
      "under_8000_hours": false,
      "nontransient_dwelling": "Any",
      "percent_oa_0_to_10": null,
      "percent_oa_10_to_20": 2500,
      "percent_oa_20_to_30": 2000,
      "percent_oa_30_to_40": 1000,
      "percent_oa_40_to_50": 500,
      "percent_oa_50_to_60": 0,
      "percent_oa_60_to_70": 0,
      "percent_oa_70_to_80": 0,
      "percent_oa_greater_than_80": 0,
      "design_conditions": "Cooling",
      "energy_recovery_effectiveness": 0.5,
      "enthalpy_recovery_ratio": null,
      "sensible_energy_recovery_ratio": null
    },
    {
      "climate_zone": "3B",
      "under_8000_hours": true,
      "nontransient_dwelling": "Any",
      "percent_oa_0_to_10": null,
      "percent_oa_10_to_20": null,
      "percent_oa_20_to_30": null,
      "percent_oa_30_to_40": null,
      "percent_oa_40_to_50": null,
      "percent_oa_50_to_60": null,
      "percent_oa_60_to_70": null,
      "percent_oa_70_to_80": null,
      "percent_oa_greater_than_80": null,
      "design_conditions": "Heating",
      "energy_recovery_effectiveness": null,
      "enthalpy_recovery_ratio": null,
      "sensible_energy_recovery_ratio": null
    },
    {
      "climate_zone": "3B",
      "under_8000_hours": false,
      "nontransient_dwelling": "Any",
      "percent_oa_0_to_10": null,
      "percent_oa_10_to_20": null,
      "percent_oa_20_to_30": 19500,
      "percent_oa_30_to_40": 9000,
      "percent_oa_40_to_50": 5000,
      "percent_oa_50_to_60": 4000,
      "percent_oa_60_to_70": 3000,
      "percent_oa_70_to_80": 1500,
      "percent_oa_greater_than_80": 0,
      "design_conditions": "Heating",
      "energy_recovery_effectiveness": 0.5,
      "enthalpy_recovery_ratio": null,
      "sensible_energy_recovery_ratio": null
    },
    {
      "climate_zone": "3B",
      "under_8000_hours": true,
      "nontransient_dwelling": "Any",
      "percent_oa_0_to_10": null,
      "percent_oa_10_to_20": null,
      "percent_oa_20_to_30": null,
      "percent_oa_30_to_40": null,
      "percent_oa_40_to_50": null,
      "percent_oa_50_to_60": null,
      "percent_oa_60_to_70": null,
      "percent_oa_70_to_80": null,
      "percent_oa_greater_than_80": null,
      "design_conditions": "Cooling",
      "energy_recovery_effectiveness": null,
      "enthalpy_recovery_ratio": null,
      "sensible_energy_recovery_ratio": null
    },
    {
      "climate_zone": "3B",
      "under_8000_hours": false,
      "nontransient_dwelling": "Any",
      "percent_oa_0_to_10": null,
      "percent_oa_10_to_20": null,
      "percent_oa_20_to_30": 19500,
      "percent_oa_30_to_40": 9000,
      "percent_oa_40_to_50": 5000,
      "percent_oa_50_to_60": 4000,
      "percent_oa_60_to_70": 3000,
      "percent_oa_70_to_80": 1500,
      "percent_oa_greater_than_80": 0,
      "design_conditions": "Cooling",
      "energy_recovery_effectiveness": 0.5,
      "enthalpy_recovery_ratio": null,
      "sensible_energy_recovery_ratio": null
    },
    {
      "climate_zone": "3C",
      "under_8000_hours": true,
      "nontransient_dwelling": "Any",
      "percent_oa_0_to_10": null,
      "percent_oa_10_to_20": null,
      "percent_oa_20_to_30": null,
      "percent_oa_30_to_40": null,
      "percent_oa_40_to_50": null,
      "percent_oa_50_to_60": null,
      "percent_oa_60_to_70": null,
      "percent_oa_70_to_80": null,
      "percent_oa_greater_than_80": null,
      "design_conditions": "Heating",
      "energy_recovery_effectiveness": null,
      "enthalpy_recovery_ratio": null,
      "sensible_energy_recovery_ratio": null
    },
    {
      "climate_zone": "3C",
      "under_8000_hours": false,
      "nontransient_dwelling": "Any",
      "percent_oa_0_to_10": null,
      "percent_oa_10_to_20": null,
      "percent_oa_20_to_30": null,
      "percent_oa_30_to_40": null,
      "percent_oa_40_to_50": null,
      "percent_oa_50_to_60": null,
      "percent_oa_60_to_70": null,
      "percent_oa_70_to_80": null,
      "percent_oa_greater_than_80": null,
      "design_conditions": "Heating",
      "energy_recovery_effectiveness": null,
      "enthalpy_recovery_ratio": null,
      "sensible_energy_recovery_ratio": null
    },
    {
      "climate_zone": "3C",
      "under_8000_hours": true,
      "nontransient_dwelling": "Any",
      "percent_oa_0_to_10": null,
      "percent_oa_10_to_20": null,
      "percent_oa_20_to_30": null,
      "percent_oa_30_to_40": null,
      "percent_oa_40_to_50": null,
      "percent_oa_50_to_60": null,
      "percent_oa_60_to_70": null,
      "percent_oa_70_to_80": null,
      "percent_oa_greater_than_80": null,
      "design_conditions": "Cooling",
      "energy_recovery_effectiveness": null,
      "enthalpy_recovery_ratio": null,
      "sensible_energy_recovery_ratio": null
    },
    {
      "climate_zone": "3C",
      "under_8000_hours": false,
      "nontransient_dwelling": "Any",
      "percent_oa_0_to_10": null,
      "percent_oa_10_to_20": null,
      "percent_oa_20_to_30": null,
      "percent_oa_30_to_40": null,
      "percent_oa_40_to_50": null,
      "percent_oa_50_to_60": null,
      "percent_oa_60_to_70": null,
      "percent_oa_70_to_80": null,
      "percent_oa_greater_than_80": null,
      "design_conditions": "Cooling",
      "energy_recovery_effectiveness": null,
      "enthalpy_recovery_ratio": null,
      "sensible_energy_recovery_ratio": null
    },
    {
      "climate_zone": "4A",
      "under_8000_hours": true,
      "nontransient_dwelling": "Any",
      "percent_oa_0_to_10": null,
      "percent_oa_10_to_20": 26000,
      "percent_oa_20_to_30": 16000,
      "percent_oa_30_to_40": 5500,
      "percent_oa_40_to_50": 4500,
      "percent_oa_50_to_60": 3500,
      "percent_oa_60_to_70": 2000,
      "percent_oa_70_to_80": 1000,
      "percent_oa_greater_than_80": 0,
      "design_conditions": "Heating",
      "energy_recovery_effectiveness": 0.5,
      "enthalpy_recovery_ratio": null,
      "sensible_energy_recovery_ratio": null
    },
    {
      "climate_zone": "4A",
      "under_8000_hours": false,
      "nontransient_dwelling": "Any",
      "percent_oa_0_to_10": null,
      "percent_oa_10_to_20": 0,
      "percent_oa_20_to_30": 0,
      "percent_oa_30_to_40": 0,
      "percent_oa_40_to_50": 0,
      "percent_oa_50_to_60": 0,
      "percent_oa_60_to_70": 0,
      "percent_oa_70_to_80": 0,
      "percent_oa_greater_than_80": 0,
      "design_conditions": "Heating",
      "energy_recovery_effectiveness": 0.5,
      "enthalpy_recovery_ratio": null,
      "sensible_energy_recovery_ratio": null
    },
    {
      "climate_zone": "4A",
      "under_8000_hours": true,
      "nontransient_dwelling": "Any",
      "percent_oa_0_to_10": null,
      "percent_oa_10_to_20": 26000,
      "percent_oa_20_to_30": 16000,
      "percent_oa_30_to_40": 5500,
      "percent_oa_40_to_50": 4500,
      "percent_oa_50_to_60": 3500,
      "percent_oa_60_to_70": 2000,
      "percent_oa_70_to_80": 1000,
      "percent_oa_greater_than_80": 0,
      "design_conditions": "Cooling",
      "energy_recovery_effectiveness": 0.5,
      "enthalpy_recovery_ratio": null,
      "sensible_energy_recovery_ratio": null
    },
    {
      "climate_zone": "4A",
      "under_8000_hours": false,
      "nontransient_dwelling": "Any",
      "percent_oa_0_to_10": null,
      "percent_oa_10_to_20": 0,
      "percent_oa_20_to_30": 0,
      "percent_oa_30_to_40": 0,
      "percent_oa_40_to_50": 0,
      "percent_oa_50_to_60": 0,
      "percent_oa_60_to_70": 0,
      "percent_oa_70_to_80": 0,
      "percent_oa_greater_than_80": 0,
      "design_conditions": "Cooling",
      "energy_recovery_effectiveness": 0.5,
      "enthalpy_recovery_ratio": null,
      "sensible_energy_recovery_ratio": null
    },
    {
      "climate_zone": "4B",
      "under_8000_hours": true,
      "nontransient_dwelling": "Any",
      "percent_oa_0_to_10": null,
      "percent_oa_10_to_20": null,
      "percent_oa_20_to_30": null,
      "percent_oa_30_to_40": null,
      "percent_oa_40_to_50": null,
      "percent_oa_50_to_60": null,
      "percent_oa_60_to_70": null,
      "percent_oa_70_to_80": null,
      "percent_oa_greater_than_80": null,
      "design_conditions": "Heating",
      "energy_recovery_effectiveness": null,
      "enthalpy_recovery_ratio": null,
      "sensible_energy_recovery_ratio": null
    },
    {
      "climate_zone": "4B",
      "under_8000_hours": false,
      "nontransient_dwelling": "Any",
      "percent_oa_0_to_10": null,
      "percent_oa_10_to_20": 2500,
      "percent_oa_20_to_30": 2000,
      "percent_oa_30_to_40": 1000,
      "percent_oa_40_to_50": 500,
      "percent_oa_50_to_60": 0,
      "percent_oa_60_to_70": 0,
      "percent_oa_70_to_80": 0,
      "percent_oa_greater_than_80": 0,
      "design_conditions": "Heating",
      "energy_recovery_effectiveness": 0.5,
      "enthalpy_recovery_ratio": null,
      "sensible_energy_recovery_ratio": null
    },
    {
      "climate_zone": "4B",
      "under_8000_hours": true,
      "nontransient_dwelling": "Any",
      "percent_oa_0_to_10": null,
      "percent_oa_10_to_20": null,
      "percent_oa_20_to_30": null,
      "percent_oa_30_to_40": null,
      "percent_oa_40_to_50": null,
      "percent_oa_50_to_60": null,
      "percent_oa_60_to_70": null,
      "percent_oa_70_to_80": null,
      "percent_oa_greater_than_80": null,
      "design_conditions": "Cooling",
      "energy_recovery_effectiveness": null,
      "enthalpy_recovery_ratio": null,
      "sensible_energy_recovery_ratio": null
    },
    {
      "climate_zone": "4B",
      "under_8000_hours": false,
      "nontransient_dwelling": "Any",
      "percent_oa_0_to_10": null,
      "percent_oa_10_to_20": 2500,
      "percent_oa_20_to_30": 2000,
      "percent_oa_30_to_40": 1000,
      "percent_oa_40_to_50": 500,
      "percent_oa_50_to_60": 0,
      "percent_oa_60_to_70": 0,
      "percent_oa_70_to_80": 0,
      "percent_oa_greater_than_80": 0,
      "design_conditions": "Cooling",
      "energy_recovery_effectiveness": 0.5,
      "enthalpy_recovery_ratio": null,
      "sensible_energy_recovery_ratio": null
    },
    {
      "climate_zone": "4C",
      "under_8000_hours": true,
      "nontransient_dwelling": "Any",
      "percent_oa_0_to_10": null,
      "percent_oa_10_to_20": null,
      "percent_oa_20_to_30": null,
      "percent_oa_30_to_40": null,
      "percent_oa_40_to_50": null,
      "percent_oa_50_to_60": null,
      "percent_oa_60_to_70": null,
      "percent_oa_70_to_80": null,
      "percent_oa_greater_than_80": null,
      "design_conditions": "Heating",
      "energy_recovery_effectiveness": null,
      "enthalpy_recovery_ratio": null,
      "sensible_energy_recovery_ratio": null
    },
    {
      "climate_zone": "4C",
      "under_8000_hours": false,
      "nontransient_dwelling": "Any",
      "percent_oa_0_to_10": null,
      "percent_oa_10_to_20": null,
      "percent_oa_20_to_30": 19500,
      "percent_oa_30_to_40": 9000,
      "percent_oa_40_to_50": 5000,
      "percent_oa_50_to_60": 4000,
      "percent_oa_60_to_70": 3000,
      "percent_oa_70_to_80": 1500,
      "percent_oa_greater_than_80": 0,
      "design_conditions": "Heating",
      "energy_recovery_effectiveness": 0.5,
      "enthalpy_recovery_ratio": null,
      "sensible_energy_recovery_ratio": null
    },
    {
      "climate_zone": "4C",
      "under_8000_hours": true,
      "nontransient_dwelling": "Any",
      "percent_oa_0_to_10": null,
      "percent_oa_10_to_20": null,
      "percent_oa_20_to_30": null,
      "percent_oa_30_to_40": null,
      "percent_oa_40_to_50": null,
      "percent_oa_50_to_60": null,
      "percent_oa_60_to_70": null,
      "percent_oa_70_to_80": null,
      "percent_oa_greater_than_80": null,
      "design_conditions": "Cooling",
      "energy_recovery_effectiveness": null,
      "enthalpy_recovery_ratio": null,
      "sensible_energy_recovery_ratio": null
    },
    {
      "climate_zone": "4C",
      "under_8000_hours": false,
      "nontransient_dwelling": "Any",
      "percent_oa_0_to_10": null,
      "percent_oa_10_to_20": null,
      "percent_oa_20_to_30": null,
      "percent_oa_30_to_40": null,
      "percent_oa_40_to_50": null,
      "percent_oa_50_to_60": null,
      "percent_oa_60_to_70": null,
      "percent_oa_70_to_80": null,
      "percent_oa_greater_than_80": null,
      "design_conditions": "Cooling",
      "energy_recovery_effectiveness": null,
      "enthalpy_recovery_ratio": null,
      "sensible_energy_recovery_ratio": null
    },
    {
      "climate_zone": "5A",
      "under_8000_hours": true,
      "nontransient_dwelling": "Any",
      "percent_oa_0_to_10": null,
      "percent_oa_10_to_20": 26000,
      "percent_oa_20_to_30": 16000,
      "percent_oa_30_to_40": 5500,
      "percent_oa_40_to_50": 4500,
      "percent_oa_50_to_60": 3500,
      "percent_oa_60_to_70": 2000,
      "percent_oa_70_to_80": 1000,
      "percent_oa_greater_than_80": 0,
      "design_conditions": "Heating",
      "energy_recovery_effectiveness": 0.5,
      "enthalpy_recovery_ratio": null,
      "sensible_energy_recovery_ratio": null
    },
    {
      "climate_zone": "5A",
      "under_8000_hours": false,
      "nontransient_dwelling": "Any",
      "percent_oa_0_to_10": null,
      "percent_oa_10_to_20": 0,
      "percent_oa_20_to_30": 0,
      "percent_oa_30_to_40": 0,
      "percent_oa_40_to_50": 0,
      "percent_oa_50_to_60": 0,
      "percent_oa_60_to_70": 0,
      "percent_oa_70_to_80": 0,
      "percent_oa_greater_than_80": 0,
      "design_conditions": "Heating",
      "energy_recovery_effectiveness": 0.5,
      "enthalpy_recovery_ratio": null,
      "sensible_energy_recovery_ratio": null
    },
    {
      "climate_zone": "5A",
      "under_8000_hours": true,
      "nontransient_dwelling": "Any",
      "percent_oa_0_to_10": null,
      "percent_oa_10_to_20": 26000,
      "percent_oa_20_to_30": 16000,
      "percent_oa_30_to_40": 5500,
      "percent_oa_40_to_50": 4500,
      "percent_oa_50_to_60": 3500,
      "percent_oa_60_to_70": 2000,
      "percent_oa_70_to_80": 1000,
      "percent_oa_greater_than_80": 0,
      "design_conditions": "Cooling",
      "energy_recovery_effectiveness": 0.5,
      "enthalpy_recovery_ratio": null,
      "sensible_energy_recovery_ratio": null
    },
    {
      "climate_zone": "5A",
      "under_8000_hours": false,
      "nontransient_dwelling": "Any",
      "percent_oa_0_to_10": null,
      "percent_oa_10_to_20": 0,
      "percent_oa_20_to_30": 0,
      "percent_oa_30_to_40": 0,
      "percent_oa_40_to_50": 0,
      "percent_oa_50_to_60": 0,
      "percent_oa_60_to_70": 0,
      "percent_oa_70_to_80": 0,
      "percent_oa_greater_than_80": 0,
      "design_conditions": "Cooling",
      "energy_recovery_effectiveness": 0.5,
      "enthalpy_recovery_ratio": null,
      "sensible_energy_recovery_ratio": null
    },
    {
      "climate_zone": "5B",
      "under_8000_hours": true,
      "nontransient_dwelling": "Any",
      "percent_oa_0_to_10": null,
      "percent_oa_10_to_20": null,
      "percent_oa_20_to_30": null,
      "percent_oa_30_to_40": null,
      "percent_oa_40_to_50": null,
      "percent_oa_50_to_60": null,
      "percent_oa_60_to_70": null,
      "percent_oa_70_to_80": null,
      "percent_oa_greater_than_80": null,
      "design_conditions": "Heating",
      "energy_recovery_effectiveness": null,
      "enthalpy_recovery_ratio": null,
      "sensible_energy_recovery_ratio": null
    },
    {
      "climate_zone": "5B",
      "under_8000_hours": false,
      "nontransient_dwelling": "Any",
      "percent_oa_0_to_10": null,
      "percent_oa_10_to_20": 2500,
      "percent_oa_20_to_30": 2000,
      "percent_oa_30_to_40": 1000,
      "percent_oa_40_to_50": 500,
      "percent_oa_50_to_60": 0,
      "percent_oa_60_to_70": 0,
      "percent_oa_70_to_80": 0,
      "percent_oa_greater_than_80": 0,
      "design_conditions": "Heating",
      "energy_recovery_effectiveness": 0.5,
      "enthalpy_recovery_ratio": null,
      "sensible_energy_recovery_ratio": null
    },
    {
      "climate_zone": "5C",
      "under_8000_hours": true,
      "nontransient_dwelling": "Any",
      "percent_oa_0_to_10": null,
      "percent_oa_10_to_20": null,
      "percent_oa_20_to_30": null,
      "percent_oa_30_to_40": null,
      "percent_oa_40_to_50": null,
      "percent_oa_50_to_60": 26000,
      "percent_oa_60_to_70": 12000,
      "percent_oa_70_to_80": 5000,
      "percent_oa_greater_than_80": 4000,
      "design_conditions": "Heating",
      "energy_recovery_effectiveness": 0.5,
      "enthalpy_recovery_ratio": null,
      "sensible_energy_recovery_ratio": null
    },
    {
      "climate_zone": "5C",
      "under_8000_hours": false,
      "nontransient_dwelling": "Any",
      "percent_oa_0_to_10": null,
      "percent_oa_10_to_20": null,
      "percent_oa_20_to_30": 19500,
      "percent_oa_30_to_40": 9000,
      "percent_oa_40_to_50": 5000,
      "percent_oa_50_to_60": 4000,
      "percent_oa_60_to_70": 3000,
      "percent_oa_70_to_80": 1500,
      "percent_oa_greater_than_80": 0,
      "design_conditions": "Heating",
      "energy_recovery_effectiveness": 0.5,
      "enthalpy_recovery_ratio": null,
      "sensible_energy_recovery_ratio": null
    },
    {
      "climate_zone": "5B",
      "under_8000_hours": true,
      "nontransient_dwelling": "Any",
      "percent_oa_0_to_10": null,
      "percent_oa_10_to_20": null,
      "percent_oa_20_to_30": null,
      "percent_oa_30_to_40": null,
      "percent_oa_40_to_50": null,
      "percent_oa_50_to_60": null,
      "percent_oa_60_to_70": null,
      "percent_oa_70_to_80": null,
      "percent_oa_greater_than_80": null,
      "design_conditions": "Cooling",
      "energy_recovery_effectiveness": null,
      "enthalpy_recovery_ratio": null,
      "sensible_energy_recovery_ratio": null
    },
    {
      "climate_zone": "5B",
      "under_8000_hours": false,
      "nontransient_dwelling": "Any",
      "percent_oa_0_to_10": null,
      "percent_oa_10_to_20": null,
      "percent_oa_20_to_30": null,
      "percent_oa_30_to_40": null,
      "percent_oa_40_to_50": null,
      "percent_oa_50_to_60": null,
      "percent_oa_60_to_70": null,
      "percent_oa_70_to_80": null,
      "percent_oa_greater_than_80": null,
      "design_conditions": "Cooling",
      "energy_recovery_effectiveness": null,
      "enthalpy_recovery_ratio": null,
      "sensible_energy_recovery_ratio": null
    },
    {
      "climate_zone": "5C",
      "under_8000_hours": true,
      "nontransient_dwelling": "Any",
      "percent_oa_0_to_10": null,
      "percent_oa_10_to_20": null,
      "percent_oa_20_to_30": null,
      "percent_oa_30_to_40": null,
      "percent_oa_40_to_50": null,
      "percent_oa_50_to_60": null,
      "percent_oa_60_to_70": null,
      "percent_oa_70_to_80": null,
      "percent_oa_greater_than_80": null,
      "design_conditions": "Cooling",
      "energy_recovery_effectiveness": null,
      "enthalpy_recovery_ratio": null,
      "sensible_energy_recovery_ratio": null
    },
    {
      "climate_zone": "5C",
      "under_8000_hours": false,
      "nontransient_dwelling": "Any",
      "percent_oa_0_to_10": null,
      "percent_oa_10_to_20": null,
      "percent_oa_20_to_30": null,
      "percent_oa_30_to_40": null,
      "percent_oa_40_to_50": null,
      "percent_oa_50_to_60": null,
      "percent_oa_60_to_70": null,
      "percent_oa_70_to_80": null,
      "percent_oa_greater_than_80": null,
      "design_conditions": "Cooling",
      "energy_recovery_effectiveness": null,
      "enthalpy_recovery_ratio": null,
      "sensible_energy_recovery_ratio": null
    },
    {
      "climate_zone": "6A",
      "under_8000_hours": true,
      "nontransient_dwelling": "Any",
      "percent_oa_0_to_10": null,
      "percent_oa_10_to_20": 26000,
      "percent_oa_20_to_30": 16000,
      "percent_oa_30_to_40": 5500,
      "percent_oa_40_to_50": 4500,
      "percent_oa_50_to_60": 3500,
      "percent_oa_60_to_70": 2000,
      "percent_oa_70_to_80": 1000,
      "percent_oa_greater_than_80": 0,
      "design_conditions": "Heating",
      "energy_recovery_effectiveness": 0.5,
      "enthalpy_recovery_ratio": null,
      "sensible_energy_recovery_ratio": null
    },
    {
      "climate_zone": "6A",
      "under_8000_hours": false,
      "nontransient_dwelling": "Any",
      "percent_oa_0_to_10": null,
      "percent_oa_10_to_20": 0,
      "percent_oa_20_to_30": 0,
      "percent_oa_30_to_40": 0,
      "percent_oa_40_to_50": 0,
      "percent_oa_50_to_60": 0,
      "percent_oa_60_to_70": 0,
      "percent_oa_70_to_80": 0,
      "percent_oa_greater_than_80": 0,
      "design_conditions": "Heating",
      "energy_recovery_effectiveness": 0.5,
      "enthalpy_recovery_ratio": null,
      "sensible_energy_recovery_ratio": null
    },
    {
      "climate_zone": "6A",
      "under_8000_hours": true,
      "nontransient_dwelling": "Any",
      "percent_oa_0_to_10": null,
      "percent_oa_10_to_20": 26000,
      "percent_oa_20_to_30": 16000,
      "percent_oa_30_to_40": 5500,
      "percent_oa_40_to_50": 4500,
      "percent_oa_50_to_60": 3500,
      "percent_oa_60_to_70": 2000,
      "percent_oa_70_to_80": 1000,
      "percent_oa_greater_than_80": 0,
      "design_conditions": "Cooling",
      "energy_recovery_effectiveness": 0.5,
      "enthalpy_recovery_ratio": null,
      "sensible_energy_recovery_ratio": null
    },
    {
      "climate_zone": "6A",
      "under_8000_hours": false,
      "nontransient_dwelling": "Any",
      "percent_oa_0_to_10": null,
      "percent_oa_10_to_20": 0,
      "percent_oa_20_to_30": 0,
      "percent_oa_30_to_40": 0,
      "percent_oa_40_to_50": 0,
      "percent_oa_50_to_60": 0,
      "percent_oa_60_to_70": 0,
      "percent_oa_70_to_80": 0,
      "percent_oa_greater_than_80": 0,
      "design_conditions": "Cooling",
      "energy_recovery_effectiveness": 0.5,
      "enthalpy_recovery_ratio": null,
      "sensible_energy_recovery_ratio": null
    },
    {
      "climate_zone": "6B",
      "under_8000_hours": true,
      "nontransient_dwelling": "Any",
      "percent_oa_0_to_10": null,
      "percent_oa_10_to_20": 28000,
      "percent_oa_20_to_30": 26500,
      "percent_oa_30_to_40": 11000,
      "percent_oa_40_to_50": 5500,
      "percent_oa_50_to_60": 4500,
      "percent_oa_60_to_70": 3500,
      "percent_oa_70_to_80": 2500,
      "percent_oa_greater_than_80": 1500,
      "design_conditions": "Heating",
      "energy_recovery_effectiveness": 0.5,
      "enthalpy_recovery_ratio": null,
      "sensible_energy_recovery_ratio": null
    },
    {
      "climate_zone": "6B",
      "under_8000_hours": false,
      "nontransient_dwelling": "Any",
      "percent_oa_0_to_10": null,
      "percent_oa_10_to_20": 0,
      "percent_oa_20_to_30": 0,
      "percent_oa_30_to_40": 0,
      "percent_oa_40_to_50": 0,
      "percent_oa_50_to_60": 0,
      "percent_oa_60_to_70": 0,
      "percent_oa_70_to_80": 0,
      "percent_oa_greater_than_80": 0,
      "design_conditions": "Heating",
      "energy_recovery_effectiveness": 0.5,
      "enthalpy_recovery_ratio": null,
      "sensible_energy_recovery_ratio": null
    },
    {
      "climate_zone": "7A",
      "under_8000_hours": true,
      "nontransient_dwelling": "Any",
      "percent_oa_0_to_10": null,
      "percent_oa_10_to_20": 4500,
      "percent_oa_20_to_30": 4000,
      "percent_oa_30_to_40": 2500,
      "percent_oa_40_to_50": 1000,
      "percent_oa_50_to_60": 0,
      "percent_oa_60_to_70": 0,
      "percent_oa_70_to_80": 0,
      "percent_oa_greater_than_80": 0,
      "design_conditions": "Heating",
      "energy_recovery_effectiveness": 0.5,
      "enthalpy_recovery_ratio": null,
      "sensible_energy_recovery_ratio": null
    },
    {
      "climate_zone": "7A",
      "under_8000_hours": false,
      "nontransient_dwelling": "Any",
      "percent_oa_0_to_10": null,
      "percent_oa_10_to_20": 0,
      "percent_oa_20_to_30": 0,
      "percent_oa_30_to_40": 0,
      "percent_oa_40_to_50": 0,
      "percent_oa_50_to_60": 0,
      "percent_oa_60_to_70": 0,
      "percent_oa_70_to_80": 0,
      "percent_oa_greater_than_80": 0,
      "design_conditions": "Heating",
      "energy_recovery_effectiveness": 0.5,
      "enthalpy_recovery_ratio": null,
      "sensible_energy_recovery_ratio": null
    },
    {
      "climate_zone": "7B",
      "under_8000_hours": true,
      "nontransient_dwelling": "Any",
      "percent_oa_0_to_10": null,
      "percent_oa_10_to_20": 4500,
      "percent_oa_20_to_30": 4000,
      "percent_oa_30_to_40": 2500,
      "percent_oa_40_to_50": 1000,
      "percent_oa_50_to_60": 0,
      "percent_oa_60_to_70": 0,
      "percent_oa_70_to_80": 0,
      "percent_oa_greater_than_80": 0,
      "design_conditions": "Heating",
      "energy_recovery_effectiveness": 0.5,
      "enthalpy_recovery_ratio": null,
      "sensible_energy_recovery_ratio": null
    },
    {
      "climate_zone": "7B",
      "under_8000_hours": false,
      "nontransient_dwelling": "Any",
      "percent_oa_0_to_10": null,
      "percent_oa_10_to_20": 0,
      "percent_oa_20_to_30": 0,
      "percent_oa_30_to_40": 0,
      "percent_oa_40_to_50": 0,
      "percent_oa_50_to_60": 0,
      "percent_oa_60_to_70": 0,
      "percent_oa_70_to_80": 0,
      "percent_oa_greater_than_80": 0,
      "design_conditions": "Heating",
      "energy_recovery_effectiveness": 0.5,
      "enthalpy_recovery_ratio": null,
      "sensible_energy_recovery_ratio": null
    },
    {
      "climate_zone": "8",
      "under_8000_hours": true,
      "nontransient_dwelling": "Any",
      "percent_oa_0_to_10": null,
      "percent_oa_10_to_20": 4500,
      "percent_oa_20_to_30": 4000,
      "percent_oa_30_to_40": 2500,
      "percent_oa_40_to_50": 1000,
      "percent_oa_50_to_60": 0,
      "percent_oa_60_to_70": 0,
      "percent_oa_70_to_80": 0,
      "percent_oa_greater_than_80": 0,
      "design_conditions": "Heating",
      "energy_recovery_effectiveness": 0.5,
      "enthalpy_recovery_ratio": null,
      "sensible_energy_recovery_ratio": null
    },
    {
      "climate_zone": "8",
      "under_8000_hours": false,
      "nontransient_dwelling": "Any",
      "percent_oa_0_to_10": null,
      "percent_oa_10_to_20": 0,
      "percent_oa_20_to_30": 0,
      "percent_oa_30_to_40": 0,
      "percent_oa_40_to_50": 0,
      "percent_oa_50_to_60": 0,
      "percent_oa_60_to_70": 0,
      "percent_oa_70_to_80": 0,
      "percent_oa_greater_than_80": 0,
      "design_conditions": "Heating",
      "energy_recovery_effectiveness": 0.5,
      "enthalpy_recovery_ratio": null,
      "sensible_energy_recovery_ratio": null
    },
    {
      "climate_zone": "6B",
      "under_8000_hours": true,
      "nontransient_dwelling": "Any",
      "percent_oa_0_to_10": null,
      "percent_oa_10_to_20": null,
      "percent_oa_20_to_30": null,
      "percent_oa_30_to_40": null,
      "percent_oa_40_to_50": null,
      "percent_oa_50_to_60": null,
      "percent_oa_60_to_70": null,
      "percent_oa_70_to_80": null,
      "percent_oa_greater_than_80": null,
      "design_conditions": "Heating",
      "energy_recovery_effectiveness": null,
      "enthalpy_recovery_ratio": null,
      "sensible_energy_recovery_ratio": null
    },
    {
      "climate_zone": "6B",
      "under_8000_hours": false,
      "nontransient_dwelling": "Any",
      "percent_oa_0_to_10": null,
      "percent_oa_10_to_20": null,
      "percent_oa_20_to_30": null,
      "percent_oa_30_to_40": null,
      "percent_oa_40_to_50": null,
      "percent_oa_50_to_60": null,
      "percent_oa_60_to_70": null,
      "percent_oa_70_to_80": null,
      "percent_oa_greater_than_80": null,
      "design_conditions": "Heating",
      "energy_recovery_effectiveness": null,
      "enthalpy_recovery_ratio": null,
      "sensible_energy_recovery_ratio": null
    },
    {
      "climate_zone": "7A",
      "under_8000_hours": true,
      "nontransient_dwelling": "Any",
      "percent_oa_0_to_10": null,
      "percent_oa_10_to_20": null,
      "percent_oa_20_to_30": null,
      "percent_oa_30_to_40": null,
      "percent_oa_40_to_50": null,
      "percent_oa_50_to_60": null,
      "percent_oa_60_to_70": null,
      "percent_oa_70_to_80": null,
      "percent_oa_greater_than_80": null,
      "design_conditions": "Heating",
      "energy_recovery_effectiveness": null,
      "enthalpy_recovery_ratio": null,
      "sensible_energy_recovery_ratio": null
    },
    {
      "climate_zone": "7A",
      "under_8000_hours": false,
      "nontransient_dwelling": "Any",
      "percent_oa_0_to_10": null,
      "percent_oa_10_to_20": null,
      "percent_oa_20_to_30": null,
      "percent_oa_30_to_40": null,
      "percent_oa_40_to_50": null,
      "percent_oa_50_to_60": null,
      "percent_oa_60_to_70": null,
      "percent_oa_70_to_80": null,
      "percent_oa_greater_than_80": null,
      "design_conditions": "Heating",
      "energy_recovery_effectiveness": null,
      "enthalpy_recovery_ratio": null,
      "sensible_energy_recovery_ratio": null
    },
    {
      "climate_zone": "7B",
      "under_8000_hours": true,
      "nontransient_dwelling": "Any",
      "percent_oa_0_to_10": null,
      "percent_oa_10_to_20": null,
      "percent_oa_20_to_30": null,
      "percent_oa_30_to_40": null,
      "percent_oa_40_to_50": null,
      "percent_oa_50_to_60": null,
      "percent_oa_60_to_70": null,
      "percent_oa_70_to_80": null,
      "percent_oa_greater_than_80": null,
      "design_conditions": "Heating",
      "energy_recovery_effectiveness": null,
      "enthalpy_recovery_ratio": null,
      "sensible_energy_recovery_ratio": null
    },
    {
      "climate_zone": "7B",
      "under_8000_hours": false,
      "nontransient_dwelling": "Any",
      "percent_oa_0_to_10": null,
      "percent_oa_10_to_20": null,
      "percent_oa_20_to_30": null,
      "percent_oa_30_to_40": null,
      "percent_oa_40_to_50": null,
      "percent_oa_50_to_60": null,
      "percent_oa_60_to_70": null,
      "percent_oa_70_to_80": null,
      "percent_oa_greater_than_80": null,
      "design_conditions": "Heating",
      "energy_recovery_effectiveness": null,
      "enthalpy_recovery_ratio": null,
      "sensible_energy_recovery_ratio": null
    },
    {
      "climate_zone": "8",
      "under_8000_hours": true,
      "nontransient_dwelling": "Any",
      "percent_oa_0_to_10": null,
      "percent_oa_10_to_20": null,
      "percent_oa_20_to_30": null,
      "percent_oa_30_to_40": null,
      "percent_oa_40_to_50": null,
      "percent_oa_50_to_60": null,
      "percent_oa_60_to_70": null,
      "percent_oa_70_to_80": null,
      "percent_oa_greater_than_80": null,
      "design_conditions": "Heating",
      "energy_recovery_effectiveness": null,
      "enthalpy_recovery_ratio": null,
      "sensible_energy_recovery_ratio": null
    },
    {
      "climate_zone": "8",
      "under_8000_hours": false,
      "nontransient_dwelling": "Any",
      "percent_oa_0_to_10": null,
      "percent_oa_10_to_20": null,
      "percent_oa_20_to_30": null,
      "percent_oa_30_to_40": null,
      "percent_oa_40_to_50": null,
      "percent_oa_50_to_60": null,
      "percent_oa_60_to_70": null,
      "percent_oa_70_to_80": null,
      "percent_oa_greater_than_80": null,
      "design_conditions": "Heating",
      "energy_recovery_effectiveness": null,
      "enthalpy_recovery_ratio": null,
      "sensible_energy_recovery_ratio": null
    }
  ]
}