[
  {
    "name": "EL1 Sys1 (PVVT) (G.ESE1)",
    "type": "PSZ-AC",
    "pszac_operation_schedule": null,
    "pszac_oa_damper_schedule": null,
    "pszac_cooling_type": "Single Speed DX AC",
    "pszac_heating_type": "Electricity",
    "pszac_fan_type": "ConstantVolume",
    "pszac_supplemental_heating_type": "Electricity",
    "space_names": [
      "EL1 ESE Perim Spc (G.ESE1)"
    ],
    "return_plenum": "EL1 ESE Perim Plnm (G.ESE5)"
  },
  {
    "name": "EL1 Sys1 (PVVT) (G.SSW2)",
    "type": "PSZ-AC",
    "pszac_operation_schedule": null,
    "pszac_oa_damper_schedule": null,
    "pszac_cooling_type": "Single Speed DX AC",
    "pszac_heating_type": "Electricity",
    "pszac_fan_type": "ConstantVolume",
    "pszac_supplemental_heating_type": "Electricity",
    "space_names": [
      "EL1 SSW Perim Spc (G.SSW2)"
    ],
    "return_plenum": "EL1 SSW Perim Plnm (G.SSW6)"
  },
  {
    "name": "EL2 Sys1 (PVVT) (G.WNW1)",
    "type": "PSZ-AC",
    "pszac_operation_schedule": null,
    "pszac_oa_damper_schedule": null,
    "pszac_cooling_type": "Single Speed DX AC",
    "pszac_heating_type": "Electricity",
    "pszac_fan_type": "ConstantVolume",
    "pszac_supplemental_heating_type": "Electricity",
    "space_names": [
      "EL2 WNW Perim Spc (G.WNW1)"
    ],
    "return_plenum": "EL2 WNW Perim Plnm (G.WNW5)"
  },
  {
    "name": "EL2 Sys1 (PVVT) (G.NNE2)",
    "type": "PSZ-AC",
    "pszac_operation_schedule": null,
    "pszac_oa_damper_schedule": null,
    "pszac_cooling_type": "Single Speed DX AC",
    "pszac_heating_type": "Electricity",
    "pszac_fan_type": "ConstantVolume",
    "pszac_supplemental_heating_type": "Electricity",
    "space_names": [
      "EL2 NNE Perim Spc (G.NNE2)"
    ],
    "return_plenum": "EL2 NNE Perim Plnm (G.NNE6)"
  }
]
