[
  {
    "name": "EL1 Sys1 (PSZ) (G.S1)",
    "type": "UnitHeater",
    "heating_type": "Gas",
    "fan_type": "OnOff",
    "fan_static_pressure": 1,
    "operation_schedule": null,
    "space_names": [
      "EL1 South Perim Spc (G.S1)"
    ]
  },
  {
    "name": "EL1 Sys1 (PSZ) (G.NE2)",
    "type": "UnitHeater",
    "heating_type": "Gas",
    "fan_type": "OnOff",
    "fan_static_pressure": 1,
    "operation_schedule": null,
    "space_names": [
      "EL1 NE Perim Spc (G.NE2)"
    ]
  },
  {
    "name": "EL1 Sys1 (PSZ) (G.SW3)",
    "type": "UnitHeater",
    "heating_type": "Gas",
    "fan_type": "OnOff",
    "fan_static_pressure": 1,
    "operation_schedule": null,
    "space_names": [
      "EL1 SW Perim Spc (G.SW3)"
    ]
  }
]
