{
  "tables": {
    "canada_national_carbon_pricing": {
      "data_type": "table",
      "refs": [
        "Obtained from Federal Carbon Pollution Pricing Benchmark https://www.canada.ca/en/environment-climate-change/services/climate-change/pricing-pollution-how-it-will-work/carbon-pollution-pricing-federal-benchmark-information.html accessed on 2025-02-18"
      ],
      "table": [
        {
          "year": 2019,
          "price_per_tonne": 20
        },
        {
          "year": 2020,
          "price_per_tonne": 30
        },
        {
          "year": 2021,
          "price_per_tonne": 40
        },
        {
          "year": 2022,
          "price_per_tonne": 50
        },
        {
          "year": 2023,
          "price_per_tonne": 65
        },
        {
          "year": 2024,
          "price_per_tonne": 80
        },
        {
          "year": 2025,
          "price_per_tonne": 95
        },
        {
          "year": 2026,
          "price_per_tonne": 110
        },
        {
          "year": 2027,
          "price_per_tonne": 125
        },
        {
          "year": 2028,
          "price_per_tonne": 140
        },
        {
          "year": 2029,
          "price_per_tonne": 155
        },
        {
          "year": 2030,
          "price_per_tonne": 170
        }
      ]
    }
  }
}